nordvpn_tray/__init__.py
nordvpn_tray/__main__.py
nordvpn_tray/resources/nvt.ico
nordvpn_tray-1.0.12.dist-info/LICENSE
nordvpn_tray-1.0.12.dist-info/METADATA
nordvpn_tray-1.0.12.dist-info/WHEEL
nordvpn_tray-1.0.12.dist-info/entry_points.txt
nordvpn_tray-1.0.12.dist-info/top_level.txt
nordvpn_tray-1.0.12.dist-info/RECORD
