Metadata-Version: 2.1
Name: nordvpn-tray
Version: 1.0.12
Summary: A cross-platform system tray application for interacting with NordVPN.
Home-page: https://github.com/aviolaris/nordvpn-tray
Author: Andreas Violaris
Keywords: nord,nordvpn,nordvpn-tray,nordvpn_tray,vpn,vpn-client,tray,python,pypi,python3,tray,tray-application,pypi-package,tray-app
Classifier: Development Status :: 7 - Inactive
Classifier: Intended Audience :: End Users/Desktop
Classifier: Operating System :: Microsoft :: Windows
Classifier: Operating System :: POSIX :: Linux
Classifier: Operating System :: MacOS
Classifier: Programming Language :: Python :: 3.8
Classifier: Programming Language :: Python :: 3.9
Classifier: Programming Language :: Python :: 3.10
Classifier: Programming Language :: Python :: 3.11
Classifier: License :: OSI Approved :: GNU General Public License v3 (GPLv3)
License-File: LICENSE
Requires-Dist: country-converter (==1.2)
Requires-Dist: Pillow (==10.2.0)
Requires-Dist: pystray (==0.19.5)
Requires-Dist: requests (==2.31.0)
Requires-Dist: setuptools (==69.2.0)
